astrafy_airflow_utils/__init__.py
astrafy_airflow_utils/airbyte.py
astrafy_airflow_utils/astrafy_environment.py
astrafy_airflow_utils/astrafy_trainning_environment.py
astrafy_airflow_utils/common_vars.py
astrafy_airflow_utils/dag_utils.py
astrafy_airflow_utils/dbt.py
astrafy_airflow_utils/elementary.py
astrafy_airflow_utils/gcs_utils.py
astrafy_airflow_utils/generate_data_dbt_training.py
astrafy_airflow_utils/k8s_utils.py
astrafy_airflow_utils/pub_sub.py
astrafy_airflow_utils/slack_alert.py
astrafy_airflow_utils-1.3.0.dist-info/METADATA
astrafy_airflow_utils-1.3.0.dist-info/WHEEL
astrafy_airflow_utils-1.3.0.dist-info/top_level.txt
astrafy_airflow_utils-1.3.0.dist-info/RECORD
