Metadata-Version: 2.4
Name: astrafy_airflow_utils
Version: 1.3.0
Summary: Astrafy Airflow utils packag3
Home-page: https://gitlab.com/python-packages3/airflow-utils
Author: Andrea Bombino
Classifier: Programming Language :: Python :: 3
Classifier: License :: OSI Approved :: MIT License
Classifier: Operating System :: OS Independent
Requires-Python: >=3.7
Dynamic: author
Dynamic: classifier
Dynamic: description
Dynamic: description-content-type
Dynamic: home-page
Dynamic: requires-python
Dynamic: summary
